setup.py
yaml_model.py
test/test_base_model.py
test/test_error_classes.py
test/test_indexes.py
test/test_load_on_access.py
test/test_model_reference.py
yaml_model.egg-info/PKG-INFO
yaml_model.egg-info/SOURCES.txt
yaml_model.egg-info/dependency_links.txt
yaml_model.egg-info/requires.txt
yaml_model.egg-info/top_level.txt