Metadata-Version: 1.0
Name: yaml-model
Version: 0.1.5
Summary: Semi-transparent YAML serialization/deserialization
Home-page: https://github.com/RickyCook/yaml_model
Author: Ricky Cook
Author-email: mail@thatpanda.com
License: UNKNOWN
Platform: UNKNOWN
